Metadata-Version: 2.1
Name: gen-value-finder
Version: 0.0.2
Summary: find the values of variables in given equation
Home-page: UNKNOWN
Author: Dhruv A. Gandhi
Author-email: dhruvalkeshkumargandhi2000@gmail.com
License: MIT
Keywords: values
Platform: UNKNOWN
Classifier: Development Status :: 5 - Production/Stable
Classifier: Intended Audience :: Education
Classifier: Operating System :: Microsoft :: Windows :: Windows 10
Classifier: License :: OSI Approved :: MIT License
Classifier: Programming Language :: Python :: 3
License-File: LICENSE.TXT
